{
    "Tools": [
        "axe",
        "pickaxe",
        "hammer",
        "shovel",
        "pitchfork",
        "razor",
        "luxury axe",
        "regal shovel",
        "opulent pickaxe",
        "saddlehorn",
        "saddle",
        "war saddle",
        "glossamer saddle",
        "brush",
        "salt lick",
		"feather pencil"
    ],
    "Light": [
        "camp fire",
        "fire pit",
        "endothermic fire",
        "endothermic fire pit",
        "torch",
        "miner's hat",
        "moggles",
        "pumpkin lantern",
        "lantern",
		"mushlight",
		"glowcap"
    ],
    "Survival": [
        "telltale heart",
        "healing salve",
        "trap",
        "bird trap",
        "umbrella",
        "bug net",
        "fishing rod",
        "pretty parasol",
        "waterballoon",
        "compass",
        "backpack",
        "straw roll",
        "whirly fan",
        "honey poultice",
        "booster shot",
        "thermal stone",
        "piggyback",
        "fur roll",
        "tent",
        "siesta lean-to",
        "luxury fan",
        "insulated pack",
		"bundling wrap"
    ],
    "Food": [
        "basic farm",
        "bee box",
        "drying rack",
        "crock pot",
        "bucket-o-poop",
        "improved farm",
        "icebox",
		"mushroom planter"
    ],
    "science": [
        "science machine",
        "alchemy engine",
        "electrical doodad",
        "thermal measurer",
        "rainometer",
        "lightning rod",
        "divining rod",
        "gun powder",
        "accomploshrine",
        "ice flingomatic",
		"cartographer's desk",
		"potter's wheel"
    ],
    "Fight": [
        "grass suit",
        "spear",
        "log suit",
        "bee mine",
        "sleep dart",
        "fire dart",
        "blow dart",
        "ham bat",
        "marble suit",
        "football helmet",
        "boomerang",
        "tooth trap",
        "scalemail",
        "weather pain",
        "morning star",
        "tail o' three cats",
		"electric dart"
    ],
    "Structures": [
        "chest",
        "sign",
        "directional sign",
        "hay wall",
        "wood wall",
        "stone wall",
        "pig house",
        "rabbit hutch",
        "bird cage",
        "cobblestones",
        "wooden flooring",
        "carpeted flooring",
        "checkerboard flooring",
        "potted fern",
        "scaled chest",
        "moon rock wall",
        "scaled flooring",
        "wardrobe",
		"mini sign",
		"end table",
		"scaled furnace",
		"friendly scarecrow",
		"wood fence",
		"wood gate",
		"potted succulent"
    ],
    "Refine": [
        "rope",
        "board",
        "cut stone",
        "papyrus",
        "thick fur",
        "purple gem",
        "nightmare fuel",
		"cratered moonrock",
		"marble bean",
		"beeswax",
		"wax paper"
    ],
    "Magic": [
        "prestihatitator",
        "shadow manipulator",
        "meat effigy",
        "pan flute",
        "one-man band",
        "night light",
        "life giving amulet",
        "chilled amulet",
        "ice staff",
        "dark sword",
        "night armour",
        "bat bat",
        "fire staff",
        "telelocator staff",
        "telelocator focus",
        "nightmare amulet",
        "belt of hunger",
		"ocuvigil",
		"moon dial"
    ],
    "Dress": [
        "garland",
        "rabbit earmuffs",
        "straw hat",
        "beefalo hat",
        "top hat",
        "fashion melon",
        "rain coat",
        "summer frest",
        "sewing kit",
        "beekeeper hat",
        "feather hat",
        "bush hat",
        "winter hat",
        "dapper vest",
        "breezy vest",
        "puffy vest",
        "ice cube",
        "cat cap",
        "rain hat",
        "hibearnation vest",
        "eyebrella",
        "floral shirt",
        "walking cane",
		"blue funcap",
		"green funcap",
		"red funcap",
		"fashion goggles",
		"desert goggles"
    ],
	"Cartography": [
		"map scroll"
	],
	"Critters": [
		"kittykit",
		"vargling",
		"ewelet",
		"broodling",
		"glomglom",
		"giblet"
	],
	"Sculpt": [
		"bubble pipe carving",
		"carved hornucopia",
		"pawn figure",
		"knight figure",
		"bishop figure",
		"rook figure",
		"queenly figure",
		"kingly figure"
	]
}